wdl2cwl/__init__.py
wdl2cwl/main.py
wdl2cwl/expression-tools/read_tsv.cwl
wdl2cwl/templates/cwltool.j2
wdl2cwl-0.2.2.dist-info/DESCRIPTION.rst
wdl2cwl-0.2.2.dist-info/METADATA
wdl2cwl-0.2.2.dist-info/RECORD
wdl2cwl-0.2.2.dist-info/WHEEL
wdl2cwl-0.2.2.dist-info/dependency_links.txt
wdl2cwl-0.2.2.dist-info/entry_points.txt
wdl2cwl-0.2.2.dist-info/metadata.json
wdl2cwl-0.2.2.dist-info/top_level.txt
