Metadata-Version: 2.0
Name: wdl2cwl
Version: 0.2.2
Summary: Convertion from WDL workflow descriptions to CWL
Home-page: https://github.com/common-workflow-language/wdl2cwl
Author: Peter Amstutz, Anton Khodak
Author-email: anton.khodak@ukr.net
License: UNKNOWN
Platform: UNKNOWN
Classifier: Development Status :: 3 - Alpha
Classifier: Operating System :: POSIX
Classifier: Intended Audience :: Developers
Classifier: Environment :: Console
Classifier: License :: OSI Approved :: Apache Software License
Requires-Dist: future
Requires-Dist: jinja2
Requires-Dist: wdl (>=1.1.0)
